<annotation>
	<folder>train</folder>
	<filename>Elon_Musk_image_11.jpeg</filename>
	<path>/home/raj/Desktop/Youtube/Object_Detection/TF_Model_Maker/project_code/dataset/train/Elon_Musk_image_11.jpeg</path>
	<source>
		<database>Unknown</database>
	</source>
	<size>
		<width>416</width>
		<height>416</height>
		<depth>3</depth>
	</size>
	<segmented>0</segmented>
	<object>
		<name>Elon_Musk</name>
		<pose>Unspecified</pose>
		<truncated>0</truncated>
		<difficult>0</difficult>
		<bndbox>
			<xmin>41</xmin>
			<ymin>19</ymin>
			<xmax>299</xmax>
			<ymax>316</ymax>
		</bndbox>
	</object>
</annotation>
